MANIFEST.in
README.md
setup.cfg
setup.py
bin/pircel
pircel/__init__.py
pircel/bot.py
pircel/model.py
pircel/protocol.py
pircel.egg-info/PKG-INFO
pircel.egg-info/SOURCES.txt
pircel.egg-info/dependency_links.txt
pircel.egg-info/not-zip-safe
pircel.egg-info/requires.txt
pircel.egg-info/top_level.txt