Metadata-Version: 1.1
Name: pircel
Version: 0.3.3
Summary: Simple IRC client library
Home-page: https://bitbucket.org/KitB/pircel/
Author: Kit Barnes
Author-email: kit@ninjalith.com
License: BSD
Keywords: irc quassel possel
Platform: UNKNOWN
Classifier: Development Status :: 2 - Pre-Alpha
Classifier: Topic :: Communications :: Chat :: Internet Relay Chat
Classifier: License :: OSI Approved :: BSD License
Classifier: Programming Language :: Python :: 3 :: Only
